quantumsymmetry/__init__.py
quantumsymmetry/core.py
quantumsymmetry/encoding.py
quantumsymmetry/qiskit_converter.py
quantumsymmetry-0.2.15.dist-info/METADATA
quantumsymmetry-0.2.15.dist-info/WHEEL
quantumsymmetry-0.2.15.dist-info/licenses/LICENSE
quantumsymmetry-0.2.15.dist-info/RECORD
