Metadata-Version: 2.4
Name: quantumsymmetry
Version: 0.2.15
Summary: Quantum computing research package
License: GNU General Public License v3.0
License-File: LICENSE
Author: Dario Picozzi
Requires-Python: >=3.7,<4.0
Classifier: License :: Other/Proprietary License
Classifier: Programming Language :: Python :: 3
Classifier: Programming Language :: Python :: 3.7
Classifier: Programming Language :: Python :: 3.8
Classifier: Programming Language :: Python :: 3.9
Classifier: Programming Language :: Python :: 3.10
Classifier: Programming Language :: Python :: 3.11
Classifier: Programming Language :: Python :: 3.12
Classifier: Programming Language :: Python :: 3.13
Classifier: Programming Language :: Python :: 3.14
Requires-Dist: ipython
Requires-Dist: numpy
Requires-Dist: openfermion
Requires-Dist: pyscf (>=2.6,<3.0)
Requires-Dist: qiskit (>=1.1,<1.2)
Requires-Dist: qiskit_nature (>=0.7,<0.8)
Requires-Dist: tabulate
